[{"q":"حلف الفضول کب پیش آئی۔","a":"ذی قعدہ میں"},{"q":"اس صحابی کا نام بتائیے جن کا نام قرآن میں آیا ہے؟","a":"حضرت زید بن حارثہ رضی اللہ عنہ"},{"q":"کعبہ کی پرانی تعمیر کو ڈھانے کی ابتداء  کس نے کی ؟","a":"ولید بن مغیرہ نے"},{"q":"تعمیر کعبہ کے وقت جب آپﷺ پتھر ڈھو رہے تھے تو آپ کو کندھے پر تہبند رکھنے کا مشورہ کس نے دیا؟","a":"حضرت عباس رضی اللہ عنہ نے"},{"q":"حضرت جبرئیل علیہ السلام جب انسانی شکل میں آتے تو کس صحابی کی شکل میں آتے ؟","a":"حضرت دحیہ کلبی کی شکل میں"},{"q":"وہ کون بزرگ ہیں جنہوں نے رسول مدعو ﴿ﷺ﴾ کی تلاش میں دور  دور سفر کئے تھے اور آخر یہ معلوم کر کے کہ وہ مکہ مکرمہ میں پیدا ہونگے اور اسی مبارک انتظار میں رہ کر انتقال کر گئے؟","a":"حضرت زید بن عمرو"},{"q":"اس زوجہ مطہرہ کا نام بتائیے جنہوں نے نبی ﷺ کیلئے اپنی باری حضرت عائشہ رضی اللہ عنہا کو ہبہ کر دیا تھا ؟","a":"حضرت سودہ رضی اللہ عنہا"},{"q":"حضرت زینب رضی اللہ عنہا کا نکاح کس سے ہوا ؟","a":"حضرت ابو العاص بن ربیع سے"},{"q":"فتح مکہ کے موقع پر اسلام قبول کر نے والے آپ ﷺ کے رضاعی بھائی کا نام بتائیے؟","a":"حضرت ابو سفیان بن حارث رضی اللہ عنہ"},{"q":"جنگ فجار کے وقت آپ ﷺ کی عمر کتنی تھی؟","a":"۱۵ /سال"}]
